pygemai-1.2.0.dist-info/licenses/LICENSE
pygemai_cli/__init__.py
pygemai_cli/main.py
pygemai-1.2.0.dist-info/METADATA
pygemai-1.2.0.dist-info/WHEEL
pygemai-1.2.0.dist-info/entry_points.txt
pygemai-1.2.0.dist-info/top_level.txt
pygemai-1.2.0.dist-info/RECORD
